pyarraypool-0.1.4.dist-info/METADATA
pyarraypool-0.1.4.dist-info/WHEEL
pyarraypool-0.1.4.dist-info/license_files/LICENSE
pyarraypool/py.typed
pyarraypool/pyarraypool.pyi
pyarraypool/__init__.py
pyarraypool/pyarraypool.cpython-310-x86_64-linux-gnu.so
pyarraypool-0.1.4.dist-info/RECORD
