Metadata-Version: 2.1
Name: pyarraypool
Version: 0.1.4
Classifier: Development Status :: 3 - Alpha
Classifier: Intended Audience :: Information Technology
Classifier: License :: OSI Approved :: MIT License
Classifier: Operating System :: POSIX :: Linux
Classifier: Operating System :: Unix
Classifier: Programming Language :: Rust
Classifier: Programming Language :: Python :: 3.8
Classifier: Programming Language :: Python :: 3.9
Classifier: Programming Language :: Python :: 3.10
Classifier: Programming Language :: Python :: Implementation :: CPython
Classifier: Topic :: Software Development :: Libraries
Requires-Dist: numpy
Requires-Dist: pytest; extra == 'test'
Requires-Dist: pytest-cov[all]; extra == 'test'
Requires-Dist: flake8; extra == 'test'
Requires-Dist: autopep8; extra == 'test'
Requires-Dist: isort; extra == 'test'
Requires-Dist: mypy; extra == 'test'
Provides-Extra: test
License-File: LICENSE
Summary: Manage pool of array using shared memory
Keywords: sharedmemory,pool,ndarray
Maintainer-email: Arthur LE MOIGNE <arthurlm@users.noreply.github.com>
Requires-Python: >=3.8
Project-URL: Source, https://github.com/arthurlm/pyarraypool
